i_did/__init__.py
i_did/cli.py
i_did-0.0.2.dist-info/entry_points.txt
i_did-0.0.2.dist-info/LICENSE
i_did-0.0.2.dist-info/WHEEL
i_did-0.0.2.dist-info/METADATA
i_did-0.0.2.dist-info/RECORD
