Metadata-Version: 2.1
Name: i-did
Version: 0.0.2
Summary: Keep track of what you did today.
Home-page: https://github.com/samueljsb/i-did
License: UNKNOWN
Author: Samuel Searles-Bryant
Author-email: devel@samueljsb.co.uk
Requires-Python: >=3.6
Classifier: Development Status :: 3 - Alpha
Classifier: License :: OSI Approved :: MIT License
Classifier: Programming Language :: Python :: 3
Requires-Dist: Click >=7.0
